aisort/__init__.py
aisort/main.py
aisort/data/chatbot.txt
aisort-0.1.4.dist-info/LICENSE
aisort-0.1.4.dist-info/METADATA
aisort-0.1.4.dist-info/WHEEL
aisort-0.1.4.dist-info/entry_points.txt
aisort-0.1.4.dist-info/top_level.txt
aisort-0.1.4.dist-info/RECORD
